cloudwatch_metrics_client/__init__.py
cloudwatch_metrics_client/aiocloudwatch.py
cloudwatch_metrics_client/cloudwatch.py
cloudwatch_metrics_client-0.0.6.dist-info/LICENSE
cloudwatch_metrics_client-0.0.6.dist-info/METADATA
cloudwatch_metrics_client-0.0.6.dist-info/WHEEL
cloudwatch_metrics_client-0.0.6.dist-info/top_level.txt
cloudwatch_metrics_client-0.0.6.dist-info/RECORD
