Metadata-Version: 2.1
Name: cloudwatch-metrics-client
Version: 0.0.6
Summary: Asynchronous (and synchronous) Python client for AWS CloudWatch metrics
Home-page: https://github.com/whale2/cloudwatch-metrics-client
Author: Nikita Makeev
Author-email: whale2.box@gmail.com
License: MIT
Platform: UNKNOWN
Classifier: Development Status :: 3 - Alpha
Classifier: Intended Audience :: Developers
Classifier: License :: OSI Approved :: MIT License
Classifier: Natural Language :: English
Classifier: Programming Language :: Python :: 3
Classifier: Programming Language :: Python :: 3.7
Classifier: Topic :: Internet
Classifier: Topic :: Software Development :: Libraries
Requires-Dist: multidict (>=4.5.2)
